draive/__init__.py
draive/anthropic/__init__.py
draive/anthropic/api.py
draive/anthropic/client.py
draive/anthropic/config.py
draive/anthropic/messages.py
draive/anthropic/utils.py
draive/aws/__init__.py
draive/aws/api.py
draive/aws/client.py
draive/aws/cloudwatch.py
draive/aws/observability.py
draive/aws/s3.py
draive/aws/sqs.py
draive/aws/state.py
draive/aws/types.py
draive/bedrock/__init__.py
draive/bedrock/api.py
draive/bedrock/client.py
draive/bedrock/config.py
draive/bedrock/converse.py
draive/bedrock/guardrails.py
draive/bedrock/models.py
draive/cohere/__init__.py
draive/cohere/api.py
draive/cohere/bedrock.py
draive/cohere/client.py
draive/cohere/config.py
draive/cohere/embedding.py
draive/conversation/__init__.py
draive/conversation/completion/__init__.py
draive/conversation/completion/default.py
draive/conversation/completion/state.py
draive/conversation/completion/types.py
draive/conversation/realtime/__init__.py
draive/conversation/realtime/default.py
draive/conversation/realtime/state.py
draive/conversation/realtime/types.py
draive/conversation/types.py
draive/embedding/__init__.py
draive/embedding/cosine.py
draive/embedding/mmr.py
draive/embedding/score.py
draive/embedding/search.py
draive/embedding/state.py
draive/embedding/types.py
draive/evaluation/__init__.py
draive/evaluation/evaluation.py
draive/evaluation/evaluator.py
draive/evaluation/scenario.py
draive/evaluation/score.py
draive/evaluation/suite.py
draive/evaluation/value.py
draive/evaluators/__init__.py
draive/evaluators/coherence.py
draive/evaluators/completeness.py
draive/evaluators/conciseness.py
draive/evaluators/consistency.py
draive/evaluators/coverage.py
draive/evaluators/creativity.py
draive/evaluators/expectations.py
draive/evaluators/factual_accuracy.py
draive/evaluators/fluency.py
draive/evaluators/groundedness.py
draive/evaluators/helpfulness.py
draive/evaluators/jailbreak.py
draive/evaluators/keywords.py
draive/evaluators/readability.py
draive/evaluators/relevance.py
draive-0.99.0.dist-info/WHEEL
draive-0.99.0.dist-info/METADATA
draive-0.99.0.dist-info/RECORD
