Metadata-Version: 2.3
Name: draive
Version: 0.99.0
Summary: Framework designed to simplify and accelerate the development of LLM-based applications.
License: MIT License
Classifier: License :: OSI Approved :: MIT License
Classifier: Intended Audience :: Developers
Classifier: Programming Language :: Python
Classifier: Programming Language :: Python :: 3
Classifier: Programming Language :: Python :: 3 :: Only
Classifier: Programming Language :: Python :: 3.13
Classifier: Typing :: Typed
Classifier: Topic :: Software Development
Classifier: Topic :: Scientific/Engineering :: Artificial Intelligence
Classifier: Topic :: Software Development :: Libraries :: Application Frameworks
Requires-Dist: numpy~=2.3
Requires-Dist: haiway~=0.43.0
Requires-Dist: anthropic~=0.75 ; extra == 'anthropic'
Requires-Dist: anthropic[bedrock]~=0.75 ; extra == 'anthropic-bedrock'
Requires-Dist: boto3~=1.41 ; extra == 'aws'
Requires-Dist: boto3~=1.41 ; extra == 'bedrock'
Requires-Dist: cohere~=5.20 ; extra == 'cohere'
Requires-Dist: cohere~=5.20 ; extra == 'cohere-bedrock'
Requires-Dist: boto3~=1.41 ; extra == 'cohere-bedrock'
Requires-Dist: bandit~=1.8 ; extra == 'dev'
Requires-Dist: pyright~=1.1 ; extra == 'dev'
Requires-Dist: pytest~=8.4 ; extra == 'dev'
Requires-Dist: pytest-asyncio~=1.2 ; extra == 'dev'
Requires-Dist: pytest-cov~=7.0 ; extra == 'dev'
Requires-Dist: ruff~=0.14 ; extra == 'dev'
Requires-Dist: mkdocs~=1.6 ; extra == 'docs'
Requires-Dist: mkdocs-material~=9.6 ; extra == 'docs'
Requires-Dist: mkdocstrings[python]~=0.30 ; extra == 'docs'
Requires-Dist: mdformat~=0.7 ; extra == 'docs'
Requires-Dist: mdformat-gfm~=0.4 ; extra == 'docs'
Requires-Dist: pymarkdownlnt~=0.9 ; extra == 'docs'
Requires-Dist: mkdocs-build-plantuml-plugin~=1.11 ; extra == 'docs'
Requires-Dist: mdformat-mkdocs>=5.1.1 ; extra == 'docs'
Requires-Dist: google-genai~=1.50 ; extra == 'gemini'
Requires-Dist: google-api-core ; extra == 'gemini'
Requires-Dist: haiway[httpx] ; extra == 'httpx'
Requires-Dist: httpx ; extra == 'httpx'
Requires-Dist: mcp~=1.21 ; extra == 'mcp'
Requires-Dist: mistralai~=1.10 ; extra == 'mistral'
Requires-Dist: ollama~=0.6.1 ; extra == 'ollama'
Requires-Dist: openai~=2.9 ; extra == 'openai'
Requires-Dist: openai[realtime]~=2.9 ; extra == 'openai-realtime'
Requires-Dist: haiway[opentelemetry] ; extra == 'opentelemetry'
Requires-Dist: opentelemetry-api ; extra == 'opentelemetry'
Requires-Dist: opentelemetry-sdk ; extra == 'opentelemetry'
Requires-Dist: opentelemetry-exporter-otlp-proto-grpc ; extra == 'opentelemetry'
Requires-Dist: haiway[postgres] ; extra == 'postgres'
Requires-Dist: asyncpg ; extra == 'postgres'
Requires-Dist: qdrant-client~=1.15.0 ; extra == 'qdrant'
Requires-Dist: haiway[rabbitmq] ; extra == 'rabbitmq'
Requires-Dist: pika ; extra == 'rabbitmq'
Requires-Dist: openai~=2.9 ; extra == 'vllm'
Maintainer: Kacper Kaliński
Maintainer-email: Kacper Kaliński <kacper.kalinski@miquido.com>
Requires-Python: >=3.13
Project-URL: Homepage, https://miquido.com
Project-URL: Repository, https://github.com/miquido/draive.git
Provides-Extra: anthropic
Provides-Extra: anthropic-bedrock
Provides-Extra: aws
Provides-Extra: bedrock
Provides-Extra: cohere
Provides-Extra: cohere-bedrock
Provides-Extra: dev
Provides-Extra: docs
Provides-Extra: gemini
Provides-Extra: httpx
Provides-Extra: mcp
Provides-Extra: mistral
Provides-Extra: ollama
Provides-Extra: openai
Provides-Extra: openai-realtime
Provides-Extra: opentelemetry
Provides-Extra: postgres
Provides-Extra: qdrant
Provides-Extra: rabbitmq
Provides-Extra: vllm
